multidyndnscli/__init__.py
multidyndnscli/cli.py
multidyndnscli/nc_dnsapi.py
multidyndnscli/schemata.py
multidyndnscli/util.py
multidyndnscli-0.1.7.dist-info/LICENSE
multidyndnscli-0.1.7.dist-info/METADATA
multidyndnscli-0.1.7.dist-info/WHEEL
multidyndnscli-0.1.7.dist-info/entry_points.txt
multidyndnscli-0.1.7.dist-info/RECORD
