Metadata-Version: 2.1
Name: multidyndnscli
Version: 0.1.7
Summary: DynDNS Command-line Client
Home-page: https://ethaden.github.io/multidyndnscli/
License: GPL-3.0-or-later
Author: Eike Thaden
Author-email: eike.thaden@gmail.com
Requires-Python: >=3.8.1,<4.0.0
Classifier: License :: OSI Approved :: GNU General Public License v3 or later (GPLv3+)
Classifier: Programming Language :: Python :: 3
Classifier: Programming Language :: Python :: 3.9
Classifier: Programming Language :: Python :: 3.10
Classifier: Programming Language :: Python :: 3.11
Requires-Dist: dnspython (>=2.3.0,<3.0.0)
Requires-Dist: fritzconnection (>=1.12.0,<2.0.0)
Requires-Dist: importlib-metadata (>=6.6.0,<7.0.0)
Requires-Dist: netaddr (>=0.8.0,<0.9.0)
Requires-Dist: netifaces2 (>=0.0.16,<0.0.17)
Requires-Dist: pyyaml (>=6.0,<7.0)
Requires-Dist: requests (>=2.28.2,<3.0.0)
Requires-Dist: schema (>=0.7.5,<0.8.0)
Project-URL: Documentation, https://ethaden.github.io/multidyndnscli/
Project-URL: Repository, https://github.com/ethaden/multidyndnscli/
